kiggle/__init__.py
kiggle/_version.py
kiggle-0.2.0.dist-info/LICENSE
kiggle-0.2.0.dist-info/METADATA
kiggle-0.2.0.dist-info/WHEEL
kiggle-0.2.0.dist-info/top_level.txt
kiggle-0.2.0.dist-info/RECORD
