Metadata-Version: 2.1
Name: kiggle
Version: 0.2.0
Summary: Utility functions for data science competitions
Home-page: https://github.com/aakashns/kiggle
Author: Aakash N S (Jovian)
Author-email: hello@jvn.io
License: UNKNOWN
Platform: UNKNOWN
Classifier: Programming Language :: Python :: 3
Classifier: License :: OSI Approved :: MIT License
Classifier: Operating System :: OS Independent
